fmqlutils/__init__.py
fmqlutils/try.py
fmqlutils/cacher/EXPLICIT_LS_CONFIGS.py
fmqlutils/cacher/LS.py
fmqlutils/cacher/__init__.py
fmqlutils/cacher/cacher.py
fmqlutils/cacher/cacherUtils.py
fmqlutils/cacher/fmqlIF.py
fmqlutils/cacher/recacheForCSTOPs.py
fmqlutils/cacher/recacher.py
fmqlutils/cacher/v2er.py
fmqlutils/reporter/__init__.py
fmqlutils/reporter/cacheHealthReporter.py
fmqlutils/reporter/reportUtils.py
fmqlutils/reporter/reportZeroAndPartials.py
fmqlutils/reporter/try.py
fmqlutils/typer/DEFAULT_TYPE_CONFIGS.py
fmqlutils/typer/__init__.py
fmqlutils/typer/reduceReportType.py
fmqlutils/typer/reduceType.py
fmqlutils/typer/reduceTypeUtils.py
fmqlutils/typer/reportReductions.py
fmqlutils-3.8.dist-info/LICENSE.txt
fmqlutils-3.8.dist-info/METADATA
fmqlutils-3.8.dist-info/WHEEL
fmqlutils-3.8.dist-info/entry_points.txt
fmqlutils-3.8.dist-info/top_level.txt
fmqlutils-3.8.dist-info/RECORD
